llm_jlm.py
llm_jlm-0.1.4.dist-info/METADATA
llm_jlm-0.1.4.dist-info/WHEEL
llm_jlm-0.1.4.dist-info/entry_points.txt
llm_jlm-0.1.4.dist-info/top_level.txt
llm_jlm-0.1.4.dist-info/RECORD
